{
  "forge_marker": 1,
  "defaults": {
    "model": "minecraft:cube_all"
  },
  "variants": {
    "material=marble,stone_variant=normal": [{
      "textures": {
        "all": "gregtech:blocks/iconsets/MARBLE_STONE"
      }
    }],
    "material=marble,stone_variant=cobblestone": [{
      "textures": {
        "all": "gregtech:blocks/iconsets/MARBLE_COBBLE"
      }
    }],
    "material=marble,stone_variant=mossy_cobblestone": [{
      "textures": {
        "all": "gregtech:blocks/iconsets/MARBLE_COBBLE_MOSSY"
      }
    }],
    "material=marble,stone_variant=bricks": [{
      "textures": {
        "all": "gregtech:blocks/iconsets/MARBLE_BRICKS"
      }
    }],
    "material=marble,stone_variant=cracked_bricks": [{
      "textures": {
        "all": "gregtech:blocks/iconsets/MARBLE_BRICKS_CRACKED"
      }
    }],
    "material=marble,stone_variant=mossy_bricks": [{
      "textures": {
        "all": "gregtech:blocks/iconsets/MARBLE_BRICKS_MOSSY"
      }
    }],
    "material=marble,stone_variant=chiseled": [{
      "textures": {
        "all": "gregtech:blocks/iconsets/MARBLE_BRICKS_CHISELED"
      }
    }],
    "material=marble,stone_variant=smooth": [{
      "textures": {
        "all": "gregtech:blocks/iconsets/MARBLE_SMOOTH"
      }
    }],

    "material=basalt,stone_variant=normal": [{
      "textures": {
        "all": "gregtech:blocks/iconsets/BASALT_STONE"
      }
    }],
    "material=basalt,stone_variant=cobblestone": [{
      "textures": {
        "all": "gregtech:blocks/iconsets/BASALT_COBBLE"
      }
    }],
    "material=basalt,stone_variant=mossy_cobblestone": [{
      "textures": {
        "all": "gregtech:blocks/iconsets/BASALT_COBBLE_MOSSY"
      }
    }],
    "material=basalt,stone_variant=bricks": [{
      "textures": {
        "all": "gregtech:blocks/iconsets/BASALT_BRICKS"
      }
    }],
    "material=basalt,stone_variant=cracked_bricks": [{
      "textures": {
        "all": "gregtech:blocks/iconsets/BASALT_BRICKS_CRACKED"
      }
    }],
    "material=basalt,stone_variant=mossy_bricks": [{
      "textures": {
        "all": "gregtech:blocks/iconsets/BASALT_BRICKS_MOSSY"
      }
    }],
    "material=basalt,stone_variant=chiseled": [{
      "textures": {
        "all": "gregtech:blocks/iconsets/BASALT_BRICKS_MOSSY"
      }
    }],
    "material=basalt,stone_variant=smooth": [{
      "textures": {
        "all": "gregtech:blocks/iconsets/BASALT_SMOOTH"
      }
    }]
  }
}