{
  "type": "gregtech:metaitem_shaped",
  "pattern": [
    "SXO",
    "P P",
    "OMW"
  ],
  "key": {
    "M": {
      "type": "gregtech:metaitem",
      "name": "electric.motor.lv"
    },
    "O": {
      "type": "forge:ore_dict",
      "ore": "ringRubber"
    },
    "X": {
      "type": "forge:ore_dict",
      "ore": "rotorTin"
    },
    "S": {
      "type": "forge:ore_dict",
      "ore": "screwTin"
    },
    "W": {
      "type": "forge:ore_dict",
      "ore": "cableGtSingleTin"
    },
    "P": {
      "type": "forge:ore_dict",
      "ore": "plateTin"
    }
  },
  "result": {
    "name": "electric.pump.lv"
  }
}